{

"products": [
  {
    "subcategory": "Tshirt",
    "name": "Printed Tshirt",
    "category": "men",
    "price": 999.99,
    "image":"https://preview.colorlib.com/theme/fashe/images/banner-02.jpg.webp"
  },
  {
    "subcategory": "Pants",
    "name": "Cropped pants",
    "category": "men",
    "price": 999.99,
    "image":"https://preview.colorlib.com/theme/fashe/images/banner-02.jpg.webp"
  },
  {
    "subcategory": "tshirt",
    "name": "Cotton Pant",
    "category": "men",
    
    "price": 19.99,
    "image":"https://preview.colorlib.com/theme/fashe/images/banner-02.jpg.webp"
  },
  {
    "subcategory": "pants",
    "name": "Sky Toner",
    "category": "men",
   
    "price": 24.99,
    "image":"https://preview.colorlib.com/theme/fashe/images/banner-02.jpg.webp"
  }
]
}

